AquaSEBS/AquaSEBS.py
AquaSEBS/__init__.py
AquaSEBS/constants.py
AquaSEBS/exceptions.py
AquaSEBS/version.py
AquaSEBS/water_heat_flux.py
aquasebs-1.3.0.dist-info/licenses/LICENSE
aquasebs-1.3.0.dist-info/METADATA
aquasebs-1.3.0.dist-info/WHEEL
aquasebs-1.3.0.dist-info/top_level.txt
aquasebs-1.3.0.dist-info/RECORD
